fla/layers/__init__.py
fla/layers/abc.py
fla/layers/attn.py
fla/layers/based.py
fla/layers/bitattn.py
fla/layers/comba.py
fla/layers/delta_net.py
fla/layers/deltaformer.py
fla/layers/forgetting_attn.py
fla/layers/gated_deltanet.py
fla/layers/gated_deltaproduct.py
fla/layers/gla.py
fla/layers/gsa.py
fla/layers/hgrn.py
fla/layers/hgrn2.py
fla/layers/kda.py
fla/layers/lightnet.py
fla/layers/linear_attn.py
fla/layers/log_linear_mamba2.py
fla/layers/mamba.py
fla/layers/mamba2.py
fla/layers/mesa_net.py
fla/layers/mla.py
fla/layers/mom.py
fla/layers/multiscale_retention.py
fla/layers/nsa.py
fla/layers/path_attn.py
fla/layers/rebased.py
fla/layers/rodimus.py
fla/layers/rwkv6.py
fla/layers/rwkv7.py
fla/layers/simple_gla.py
fla/layers/utils.py
fla/models/__init__.py
fla/models/modeling_layers.py
fla/models/utils.py
fla/models/abc/__init__.py
fla/models/abc/configuration_abc.py
fla/models/abc/modeling_abc.py
fla/models/bitnet/__init__.py
fla/models/bitnet/configuration_bitnet.py
fla/models/bitnet/modeling_bitnet.py
fla/models/comba/__init__.py
fla/models/comba/configuration_comba.py
fla/models/comba/modeling_comba.py
fla/models/delta_net/__init__.py
fla/models/delta_net/configuration_delta_net.py
fla/models/delta_net/modeling_delta_net.py
fla/models/deltaformer/__init__.py
fla/models/deltaformer/configuration_deltaformer.py
fla/models/deltaformer/modeling_deltaformer.py
fla/models/forgetting_transformer/__init__.py
fla/models/forgetting_transformer/configuration_forgetting_transformer.py
fla/models/forgetting_transformer/modeling_forgetting_transformer.py
fla/models/gated_deltanet/__init__.py
fla/models/gated_deltanet/configuration_gated_deltanet.py
fla/models/gated_deltanet/modeling_gated_deltanet.py
fla/models/gated_deltaproduct/__init__.py
fla/models/gated_deltaproduct/configuration_gated_deltaproduct.py
fla/models/gated_deltaproduct/modeling_gated_deltaproduct.py
fla/models/gla/__init__.py
fla/models/gla/configuration_gla.py
fla/models/gla/modeling_gla.py
flash_linear_attention-0.4.1.dist-info/licenses/LICENSE
flash_linear_attention-0.4.1.dist-info/METADATA
flash_linear_attention-0.4.1.dist-info/WHEEL
flash_linear_attention-0.4.1.dist-info/top_level.txt
flash_linear_attention-0.4.1.dist-info/RECORD
