Metadata-Version: 2.4
Name: flash-linear-attention
Version: 0.4.1
Summary: Fast linear attention models and layers
Project-URL: Homepage, https://github.com/fla-org/flash-linear-attention
Project-URL: Repository, https://github.com/fla-org/flash-linear-attention
Requires-Python: >=3.10
License-File: LICENSE
Requires-Dist: fla-core==0.4.1
Requires-Dist: transformers
Provides-Extra: conv1d
Requires-Dist: causal-conv1d>=1.4.0; extra == "conv1d"
Provides-Extra: benchmark
Requires-Dist: matplotlib; extra == "benchmark"
Requires-Dist: datasets>=3.3.0; extra == "benchmark"
Provides-Extra: test
Requires-Dist: pytest; extra == "test"
Dynamic: license-file
